model_stats/__init__.py
model_stats/urls.py
model_stats/views.py
model_stats/templates/model_stats/stats.html
django_model_stats-0.0.2.dist-info/LICENSE
django_model_stats-0.0.2.dist-info/METADATA
django_model_stats-0.0.2.dist-info/WHEEL
django_model_stats-0.0.2.dist-info/top_level.txt
django_model_stats-0.0.2.dist-info/RECORD
