Metadata-Version: 2.1
Name: django-model-stats
Version: 0.0.2
Summary: Display how often models and model fields are used in the database
Home-page: https://github.com/xi/django-model-stats
Author: Tobias Bengfort
Author-email: tobias.bengfort@posteo.de
License: MIT
Platform: UNKNOWN
Classifier: Development Status :: 4 - Beta
Classifier: Environment :: Web Environment
Classifier: Framework :: Django
Classifier: Framework :: Django :: 3.2
Classifier: Intended Audience :: Developers
Classifier: License :: OSI Approved :: MIT License
Classifier: Operating System :: OS Independent
Classifier: Programming Language :: Python
Classifier: Programming Language :: Python :: 3
License-File: LICENSE
